<?xml version="1.0" encoding="UTF-8"?>
<MetaDataObject xmlns="http://v8.1c.ru/8.3/MDClasses" xmlns:app="http://v8.1c.ru/8.2/managed-application/core" xmlns:cfg="http://v8.1c.ru/8.1/data/enterprise/current-config" xmlns:cmi="http://v8.1c.ru/8.2/managed-application/cmi" xmlns:ent="http://v8.1c.ru/8.1/data/enterprise" xmlns:lf="http://v8.1c.ru/8.2/managed-application/logform" xmlns:style="http://v8.1c.ru/8.1/data/ui/style" xmlns:sys="http://v8.1c.ru/8.1/data/ui/fonts/system" xmlns:v8="http://v8.1c.ru/8.1/data/core" xmlns:v8ui="http://v8.1c.ru/8.1/data/ui" xmlns:web="http://v8.1c.ru/8.1/data/ui/colors/web" xmlns:win="http://v8.1c.ru/8.1/data/ui/colors/windows" xmlns:xen="http://v8.1c.ru/8.3/xcf/enums" xmlns:xpr="http://v8.1c.ru/8.3/xcf/predef" xmlns:xr="http://v8.1c.ru/8.3/xcf/readable" xmlns:xs="http://www.w3.org/2001/XMLSchema" xmlns:xsi="http://www.w3.org/2001/XMLSchema-instance" version="2.18">
	<DocumentJournal uuid="3150695a-a5b9-44e1-98f4-8ed1a40cd763">
		<InternalInfo>
			<xr:GeneratedType name="DocumentJournalSelection.УчетКандидатовНаРаботу" category="Selection">
				<xr:TypeId>5e9312da-ba37-47a7-94b9-83af303eae2c</xr:TypeId>
				<xr:ValueId>167b00d0-b695-4b5b-aa93-2735550617b7</xr:ValueId>
			</xr:GeneratedType>
			<xr:GeneratedType name="DocumentJournalList.УчетКандидатовНаРаботу" category="List">
				<xr:TypeId>c7534b3b-5ceb-4d8e-87ae-8f0079f6d9b5</xr:TypeId>
				<xr:ValueId>c9f3ee98-e42a-4e38-9c5a-2aed5f19d19c</xr:ValueId>
			</xr:GeneratedType>
			<xr:GeneratedType name="DocumentJournalManager.УчетКандидатовНаРаботу" category="Manager">
				<xr:TypeId>522d7c3d-fc76-46a9-a954-dab986fb93dc</xr:TypeId>
				<xr:ValueId>3b440b71-1c16-48b1-acd0-19b63c86c88c</xr:ValueId>
			</xr:GeneratedType>
		</InternalInfo>
		<Properties>
			<Name>УчетКандидатовНаРаботу</Name>
			<Synonym>
				<v8:item>
					<v8:lang>ru</v8:lang>
					<v8:content>Учет кандидатов на работу</v8:content>
				</v8:item>
			</Synonym>
			<Comment/>
			<DefaultForm>DocumentJournal.УчетКандидатовНаРаботу.Form.ФормаСписка</DefaultForm>
			<AuxiliaryForm/>
			<UseStandardCommands>false</UseStandardCommands>
			<RegisteredDocuments>
				<xr:Item xsi:type="xr:MDObjectRef">Document.ОценкаКандидата</xr:Item>
				<xr:Item xsi:type="xr:MDObjectRef">Document.РегистрацияКандидатов</xr:Item>
				<xr:Item xsi:type="xr:MDObjectRef">Document.ОценкаИспытательногоСрока</xr:Item>
				<xr:Item xsi:type="xr:MDObjectRef">Document.РегистрацияСобеседованияКандидата</xr:Item>
			</RegisteredDocuments>
			<IncludeHelpInContents>false</IncludeHelpInContents>
			<ListPresentation/>
			<ExtendedListPresentation/>
			<Explanation/>
		</Properties>
		<ChildObjects>
			<Column uuid="c3905a1d-27b3-423d-bf85-6abe74b6bdf6">
				<Properties>
					<Name>Ответственный</Name>
					<Synonym>
						<v8:item>
							<v8:lang>ru</v8:lang>
							<v8:content>Ответственный</v8:content>
						</v8:item>
					</Synonym>
					<Comment/>
					<Indexing>DontIndex</Indexing>
					<References>
						<xr:Item xsi:type="xr:MDObjectRef">Document.ОценкаКандидата.Attribute.Ответственный</xr:Item>
						<xr:Item xsi:type="xr:MDObjectRef">Document.ОценкаИспытательногоСрока.Attribute.Ответственный</xr:Item>
						<xr:Item xsi:type="xr:MDObjectRef">Document.РегистрацияКандидатов.Attribute.Ответственный</xr:Item>
						<xr:Item xsi:type="xr:MDObjectRef">Document.РегистрацияСобеседованияКандидата.Attribute.Ответственный</xr:Item>
					</References>
				</Properties>
			</Column>
			<Column uuid="f9a3ba1a-85ae-440b-a328-65778f821f47">
				<Properties>
					<Name>Комментарий</Name>
					<Synonym>
						<v8:item>
							<v8:lang>ru</v8:lang>
							<v8:content>Комментарий</v8:content>
						</v8:item>
					</Synonym>
					<Comment/>
					<Indexing>DontIndex</Indexing>
					<References>
						<xr:Item xsi:type="xr:MDObjectRef">Document.ОценкаКандидата.Attribute.Комментарий</xr:Item>
						<xr:Item xsi:type="xr:MDObjectRef">Document.ОценкаИспытательногоСрока.Attribute.Комментарий</xr:Item>
						<xr:Item xsi:type="xr:MDObjectRef">Document.РегистрацияКандидатов.Attribute.Комментарий</xr:Item>
						<xr:Item xsi:type="xr:MDObjectRef">Document.РегистрацияСобеседованияКандидата.Attribute.Комментарий</xr:Item>
					</References>
				</Properties>
			</Column>
			<Column uuid="131df5c2-f88a-4f8a-a42a-6e9bc64077d7">
				<Properties>
					<Name>РучнаяКорректировка</Name>
					<Synonym>
						<v8:item>
							<v8:lang>ru</v8:lang>
							<v8:content>Ручная корректировка</v8:content>
						</v8:item>
					</Synonym>
					<Comment/>
					<Indexing>DontIndex</Indexing>
					<References>
						<xr:Item xsi:type="xr:MDObjectRef">Document.РегистрацияСобеседованияКандидата.Attribute.РучнаяКорректировка</xr:Item>
						<xr:Item xsi:type="xr:MDObjectRef">Document.ОценкаИспытательногоСрока.Attribute.РучнаяКорректировка</xr:Item>
						<xr:Item xsi:type="xr:MDObjectRef">Document.ОценкаКандидата.Attribute.РучнаяКорректировка</xr:Item>
						<xr:Item xsi:type="xr:MDObjectRef">Document.РегистрацияКандидатов.Attribute.РучнаяКорректировка</xr:Item>
					</References>
				</Properties>
			</Column>
			<Form>ФормаСписка</Form>
		</ChildObjects>
	</DocumentJournal>
</MetaDataObject>